bgrafana_api/__init__.py
bgrafana_api/api_client.py
bgrafana_api/api_response.py
bgrafana_api/configuration.py
bgrafana_api/exceptions.py
bgrafana_api/py.typed
bgrafana_api/rest.py
bgrafana_api/api/__init__.py
bgrafana_api/api/access_control_api.py
bgrafana_api/api/access_control_provisioning_api.py
bgrafana_api/api/admin_api.py
bgrafana_api/api/admin_ldap_api.py
bgrafana_api/api/admin_provisioning_api.py
bgrafana_api/api/admin_users_api.py
bgrafana_api/api/annotations_api.py
bgrafana_api/api/api_keys_api.py
bgrafana_api/api/correlations_api.py
bgrafana_api/api/dashboard_permissions_api.py
bgrafana_api/api/dashboard_versions_api.py
bgrafana_api/api/dashboards_api.py
bgrafana_api/api/datasource_permissions_api.py
bgrafana_api/api/datasources_api.py
bgrafana_api/api/ds_api.py
bgrafana_api/api/enterprise_api.py
bgrafana_api/api/folder_permissions_api.py
bgrafana_api/api/folders_api.py
bgrafana_api/api/get_current_org_api.py
bgrafana_api/api/ldap_debug_api.py
bgrafana_api/api/legacy_alerts_api.py
bgrafana_api/api/legacy_alerts_notification_channels_api.py
bgrafana_api/api/library_elements_api.py
bgrafana_api/api/licensing_api.py
bgrafana_api/api/org_api.py
bgrafana_api/api/org_invites_api.py
bgrafana_api/api/org_preferences_api.py
bgrafana_api/api/orgs_api.py
bgrafana_api/api/playlists_api.py
bgrafana_api/api/provisioning_api.py
bgrafana_api/api/query_history_api.py
bgrafana_api/api/recording_rules_api.py
bgrafana_api/api/reports_api.py
bgrafana_api/api/saml_api.py
bgrafana_api/api/search_api.py
bgrafana_api/api/service_accounts_api.py
bgrafana_api/api/signed_in_user_api.py
bgrafana_api/api/snapshots_api.py
bgrafana_api/api/sync_team_groups_api.py
bgrafana_api/api/teams_api.py
bgrafana_api/api/user_preferences_api.py
bgrafana_api/api/users_api.py
bgrafana_api/models/__init__.py
bgrafana_api/models/active_sync_status_dto.py
bgrafana_api/models/active_user_stats.py
bgrafana_api/models/add_command.py
bgrafana_api-0.0.7.dist-info/DESCRIPTION.rst
bgrafana_api-0.0.7.dist-info/METADATA
bgrafana_api-0.0.7.dist-info/RECORD
bgrafana_api-0.0.7.dist-info/WHEEL
bgrafana_api-0.0.7.dist-info/metadata.json
bgrafana_api-0.0.7.dist-info/top_level.txt
