Metadata-Version: 2.0
Name: bgrafana-api
Version: 0.0.7
Summary: Grafana HTTP API.
Home-page: UNKNOWN
Author: Grafana Labs
Author-email: hello@grafana.com
License: UNKNOWN
Keywords: OpenAPI,OpenAPI-Generator,Grafana HTTP API.
Platform: UNKNOWN
Requires-Dist: aenum
Requires-Dist: pydantic (<2,>=1.10.5)
Requires-Dist: python-dateutil
Requires-Dist: urllib3 (<2.1.0,>=1.25.3)
